tgviz/__init__.py
tgviz/client.py
tgviz/middleware.py
tgviz-0.1.3.dist-info/LICENSE
tgviz-0.1.3.dist-info/METADATA
tgviz-0.1.3.dist-info/WHEEL
tgviz-0.1.3.dist-info/top_level.txt
tgviz-0.1.3.dist-info/RECORD
