Metadata-Version: 2.2
Name: tgviz
Version: 0.1.3
Summary: Universal asynchronous library for posting Telegram Updates to TGViz API
Author: TGVIZ
Author-email: tgvizapi@gmail.com
Classifier: Programming Language :: Python :: 3
Classifier: Operating System :: OS Independent
Requires-Python: >=3.7
License-File: LICENSE
Requires-Dist: httpx>=0.23.0
Requires-Dist: pydantic>=1.8.0
Dynamic: author
Dynamic: author-email
Dynamic: classifier
Dynamic: description
Dynamic: description-content-type
Dynamic: requires-dist
Dynamic: requires-python
Dynamic: summary
